{
  "equipos": [
    { "id": "1A", "nombre": "Club All Boys Pasto", "escudo": "https://res.cloudinary.com/dny2fuvgi/image/upload/v1753187077/image_3_fr6cjd.svg", "grupo": "A" },
    { "id": "2A", "nombre": "Real Madrid De Túmaco", "escudo": "https://res.cloudinary.com/dny2fuvgi/image/upload/v1753187078/image_11_axjztd.svg", "grupo": "A" },
    { "id": "3A", "nombre": "Aldrin Túmaco", "escudo": "https://res.cloudinary.com/dny2fuvgi/image/upload/v1753187076/image_1_d0sxvo.svg", "grupo": "A" },
    { "id": "4A", "nombre": "JLC Ancuya", "escudo": "https://res.cloudinary.com/dny2fuvgi/image/upload/v1753187078/image_9_mjo6gb.svg", "grupo": "A" },
    { "id": "1B", "nombre": "Deportivo Pasto", "escudo":  "https://res.cloudinary.com/dny2fuvgi/image/upload/v1753187077/image_6_e7ds7z.svg", "grupo": "B" },
    { "id": "2B", "nombre": "Independ. F. C.", "escudo": "https://res.cloudinary.com/dny2fuvgi/image/upload/v1753187078/image_7_ccjtog.svg", "grupo": "B" },
    { "id": "3B", "nombre": "Radi F. C. Ipiales", "escudo": "https://res.cloudinary.com/dny2fuvgi/image/upload/v1753187078/image_10_uphqv6.svg", "grupo": "B" },
    { "id": "4B", "nombre": "Alianza Sureña", "escudo": "https://res.cloudinary.com/dny2fuvgi/image/upload/v1753187077/image_2_oe6wqk.svg", "grupo": "B" },
    { "id": "1C", "nombre": "Sporting de Nariño Rio Real", "escudo": "https://res.cloudinary.com/dny2fuvgi/image/upload/v1753187077/image_4_dia6fx.svg", "grupo": "C" },
    { "id": "2C", "nombre": "Mayorga F.C.", "escudo": "https://res.cloudinary.com/dny2fuvgi/image/upload/v1753187078/image_8_euxr84.svg", "grupo": "C" },
    { "id": "3C", "nombre": "Pedregal F.C.", "escudo": "https://res.cloudinary.com/dny2fuvgi/image/upload/v1753187077/image_5_rado3x.svg", "grupo": "C" },
    { "id": "4C", "nombre": "Águilas F.C.", "escudo": "https://res.cloudinary.com/dny2fuvgi/image/upload/v1753187078/image_12_xwfybu.svg", "grupo": "C" }
  ],
  "partidos": [
   {
    "id": 1,
    "fecha": "2025-07-22",
    "hora": "14:30",
    "fase": "Grupos",
    "grupo": "C",
    "equipoLocal": "1C",
    "equipoVisitante": "2C",
    "golesLocal": 1,
    "golesVisitante": 0,
    "estado": "finalizado"
  },
  {
    "id": 2,
    "fecha": "2025-07-22",
    "hora": "15:45",
    "fase": "Grupos",
    "grupo": "B",
    "equipoLocal": "1B",
    "equipoVisitante": "2B",
    "golesLocal": 2,
    "golesVisitante": 1,
    "estado": "finalizado"
  },
  {
    "id": 3,
    "fecha": "2025-07-22",
    "hora": "17:00",
    "fase": "Grupos",
    "grupo": "A",
    "equipoLocal": "1A",
    "equipoVisitante": "2A",
    "golesLocal": 0,
    "golesVisitante": 3,
    "estado": "finalizado"
  },
  {
    "id": 4,
    "fecha": "2025-07-23",
    "hora": "14:00",
    "fase": "Grupos",
    "grupo": "A",
    "equipoLocal": "3A",
    "equipoVisitante": "4A",
    "golesLocal": 2,
    "golesVisitante": 0
    ,
    "estado": "Por Iniciar"
  },
  {
    "id": 5,
    "fecha": "2025-07-23",
    "hora": "15:15",
    "fase": "Grupos",
    "grupo": "B",
    "equipoLocal": "3B",
    "equipoVisitante": "4B",
    "golesLocal": null,
    "golesVisitante": null,
    "estado": "Por Iniciar"
  },
  {
    "id": 6,
    "fecha": "2025-07-23",
    "hora": "16:30",
    "fase": "Grupos",
    "grupo": "C",
    "equipoLocal": "3C",
    "equipoVisitante": "4C",
    "golesLocal": null,
    "golesVisitante": null,
    "estado": "Por Iniciar"
  },
  {
    "id": 7,
    "fecha": "2025-07-24",
    "hora": "09:30",
    "fase": "Grupos",
    "grupo": "C",
    "equipoLocal": "2C",
    "equipoVisitante": "3C",
    "golesLocal": null,
    "golesVisitante": null,
    "estado": "Por Iniciar"
  },
  {
    "id": 8,
    "fecha": "2025-07-24",
    "hora": "10:45",
    "fase": "Grupos",
    "grupo": "B",
    "equipoLocal": "2B",
    "equipoVisitante": "3B",
    "golesLocal": null,
    "golesVisitante": null,
    "estado": "Por Iniciar"
  },
  {
    "id": 9,
    "fecha": "2025-07-24",
    "hora": "12:00",
    "fase": "Grupos",
    "grupo": "A",
    "equipoLocal": "2A",
    "equipoVisitante": "3A",
    "golesLocal": null,
    "golesVisitante": null,
    "estado": "Por Iniciar"
  },
  {
    "id": 10,
    "fecha": "2025-07-24",
    "hora": "01:15",
    "fase": "Grupos",
    "grupo": "C",
    "equipoLocal": "4C",
    "equipoVisitante": "1C",
    "golesLocal": null,
    "golesVisitante": null,
    "estado": "Por Iniciar"
  },
  {
    "id": 11,
    "fecha": "2025-07-24",
    "hora": "02:30",
    "fase": "Grupos",
    "grupo": "B",
    "equipoLocal": "4B",
    "equipoVisitante": "1B",
    "golesLocal": null,
    "golesVisitante": null,
    "estado": "Por Iniciar"
  },
  {
    "id": 12,
    "fecha": "2025-07-24",
    "hora": "03:45",
    "fase": "Grupos",
    "grupo": "A",
    "equipoLocal": "4A",
    "equipoVisitante": "1A",
    "golesLocal": null,
    "golesVisitante": null,
    "estado": "Por Iniciar"
  },
  {
    "id": 13,
    "fecha": "2025-07-25",
    "hora": "09:30",
    "fase": "Grupos",
    "grupo": "C",
    "equipoLocal": "4C",
    "equipoVisitante": "2C",
    "golesLocal": null,
    "golesVisitante": null,
    "estado": "Por Iniciar"
  },
  {
    "id": 14,
    "fecha": "2025-07-25",
    "hora": "10:45",
    "fase": "Grupos",
    "grupo": "B",
    "equipoLocal": "4B",
    "equipoVisitante": "2B",
    "golesLocal": null,
    "golesVisitante": null,
    "estado": "Por Iniciar"
  },
  {
    "id": 15,
    "fecha": "2025-07-25",
    "hora": "12:00",
    "fase": "Grupos",
    "grupo": "A",
    "equipoLocal": "4A",
    "equipoVisitante": "2A",
    "golesLocal": null,
    "golesVisitante": null,
    "estado": "Por Iniciar"
  },
  {
    "id": 16,
    "fecha": "2025-07-25",
    "hora": "01:15",
    "fase": "Grupos",
    "grupo": "C",
    "equipoLocal": "3C",
    "equipoVisitante": "1C",
    "golesLocal": null,
    "golesVisitante": null,
    "estado": "Por Iniciar"
  },
  {
    "id": 17,
    "fecha": "2025-07-25",
    "hora": "02:30",
    "fase": "Grupos",
    "grupo": "B",
    "equipoLocal": "3B",
    "equipoVisitante": "1B",
    "golesLocal": null,
    "golesVisitante": null,
    "estado": "Por Iniciar"
  },
  {
    "id": 18,
    "fecha": "2025-07-25",
    "hora": "03:45",
    "fase": "Grupos",
    "grupo": "A",
    "equipoLocal": "3A",
    "equipoVisitante": "1A",
    "golesLocal": null,
    "golesVisitante": null,
    "estado": "Por Iniciar"
  },
  {
    "id": 19,
    "fecha": "2025-07-26",
    "hora": "08:00",
    "fase": "Cuartos de Final",
    "grupo": null,
    "equipoLocal": "2A",
    "equipoVisitante": "1B",
    "golesLocal": null,
    "golesVisitante": null,
    "estado": "Por Iniciar"
  },
  {
    "id": 20,
    "fecha": "2025-07-26",
    "hora": "09:15",
    "fase": "Cuartos de Final",
    "grupo": null,
    "equipoLocal": "1C",
    "equipoVisitante": "4B",
    "golesLocal": null,
    "golesVisitante": null,
    "estado": "Por Iniciar"
  },
  {
    "id": 21,
    "fecha": "2025-07-26",
    "hora": "10:30",
    "fase": "Cuartos de Final",
    "grupo": null,
    "equipoLocal": "3B",
    "equipoVisitante": "2C",
    "golesLocal": null,
    "golesVisitante": null,
    "estado": "Por Iniciar"
  },
  {
    "id": 22,
    "fecha": "2025-07-26",
    "hora": "11:45",
    "fase": "Cuartos de Final",
    "grupo": null,
    "equipoLocal": "3A",
    "equipoVisitante": "4C",
    "golesLocal": null,
    "golesVisitante": null,
    "estado": "Por Iniciar"
  },
  {
    "id": 23,
    "fecha": "2025-07-26",
    "hora": "15:45",
    "fase": "Semifinal",
    "grupo": null,
    "equipoLocal": "GP1",
    "equipoVisitante": "GP4",
    "golesLocal": null,
    "golesVisitante": null,
    "estado": "Por Iniciar"
  },
  {
    "id": 24,
    "fecha": "2025-07-26",
    "hora": "17:00",
    "fase": "Semifinal",
    "grupo": null,
    "equipoLocal": "GP2",
    "equipoVisitante": "GP3",
    "golesLocal": null,
    "golesVisitante": null,
    "estado": "Por Iniciar"
  },
  {
    "id": 25,
    "fecha": "2025-07-27",
    "hora": "09:15",
    "fase": "Tercer Puesto",
    "grupo": null,
    "equipoLocal": "PE1",
    "equipoVisitante": "PE2",
    "golesLocal": null,
    "golesVisitante": null,
    "estado": "Por Iniciar"
  },
  {
    "id": 26,
    "fecha": "2025-07-27",
    "hora": "10:30",
    "fase": "Final",
    "grupo": null,
    "equipoLocal": "GE1",
    "equipoVisitante": "GE2",
    "golesLocal": null,
    "golesVisitante": null,
    "estado": "Por Iniciar"
  }
  ]
}
